identityfield/__init__.py
identityfield/apps.py
django_identityfield-0.1.1.dist-info/WHEEL
django_identityfield-0.1.1.dist-info/METADATA
django_identityfield-0.1.1.dist-info/RECORD
