Metadata-Version: 2.3
Name: django-identityfield
Version: 0.1.1
Summary: 
Requires-Dist: django
Requires-Python: >=3.13
